poetry_auto_version/plugin.py
poetry_auto_version/test_plugin.py
poetry_auto_version-0.0.1.dist-info/entry_points.txt
poetry_auto_version-0.0.1.dist-info/LICENSE
poetry_auto_version-0.0.1.dist-info/WHEEL
poetry_auto_version-0.0.1.dist-info/METADATA
poetry_auto_version-0.0.1.dist-info/RECORD
